mattlib/API_factory.py
mattlib/BaseAPI.py
mattlib/__init__.py
mattlib/adobe/AdobeAPI.py
mattlib/adobe/__init__.py
mattlib/clockify/ClockifyAPI.py
mattlib/clockify/__init__.py
mattlib/customized/CustomizedAPI.py
mattlib/customized/__init__.py
mattlib/docusign/DocusignAPI.py
mattlib/docusign/__init__.py
mattlib/google/BaseGoogleAPI.py
mattlib/google/GCPAPI.py
mattlib/google/GoogleWorkspaceAPI.py
mattlib/google/PubSub.py
mattlib/google/SQL.py
mattlib/google/Storage.py
mattlib/google/__init__.py
mattlib/microsoft/AzureAPI.py
mattlib/microsoft/BaseMicrosoftAPI.py
mattlib/microsoft/EntraIdAPI.py
mattlib/microsoft/GraphAPI.py
mattlib/microsoft/__init__.py
mattlib/network/HttpListener.py
mattlib/network/__init__.py
mattlib/salesforce/SalesForceAPI.py
mattlib/salesforce/__init__.py
mattlib/snow/__init__.py
mattlib/snow/snowAPI.py
mattlib/system/Logger.py
mattlib/system/__init__.py
mattlibversion_1.6.4-0.0.0.dist-info/COPYING
mattlibversion_1.6.4-0.0.0.dist-info/METADATA
mattlibversion_1.6.4-0.0.0.dist-info/WHEEL
mattlibversion_1.6.4-0.0.0.dist-info/top_level.txt
mattlibversion_1.6.4-0.0.0.dist-info/RECORD
