Metadata-Version: 2.1
Name: mattlibversion-1.6.4
Version: 0.0.0
Summary: API data extraction and formatting utilities.
Home-page: https://source.cloud.google.com/mtz-repos-global/mattlib
Author: 4matt
Author-email: mattzero@4matt.com.br
Classifier: Programming Language :: Python :: 3
Classifier: License :: OSI Approved :: GNU General Public License v3 (GPLv3)
Classifier: Operating System :: OS Independent
Requires-Python: >=3.8
License-File: COPYING
Requires-Dist: requests
Requires-Dist: pandas
Requires-Dist: certifi
Requires-Dist: flask
Requires-Dist: google-api-python-client
Requires-Dist: google-cloud-storage
Requires-Dist: sqlalchemy
Requires-Dist: jwt
